{
  "suite": "ghostty",
  "file": "Terminal.zig",
  "testName": "Terminal: print multicodepoint grapheme, mode 2027",
  "sourceLine": 4353,
  "zigBody": "test \"Terminal: print multicodepoint grapheme, mode 2027\" {\n    var t = try init(testing.allocator, .{ .cols = 80, .rows = 80 });\n    defer t.deinit(testing.allocator);\n\n    // Enable grapheme clustering\n    t.modes.set(.grapheme_cluster, true);\n\n    // https://github.com/mitchellh/ghostty/issues/289\n    // This is: 👨‍👩‍👧 (which may or may not render correctly)\n    try t.print(0x1F468);\n    try t.print(0x200D);\n    try t.print(0x1F469);\n    try t.print(0x200D);\n    try t.print(0x1F467);\n\n    // We should have 2 cells taken up. It is one character but \"wide\".\n    try testing.expectEqual(@as(usize, 0), t.screens.active.cursor.y);\n    try testing.expectEqual(@as(usize, 2), t.screens.active.cursor.x);\n\n    // Row should be dirty\n    try testing.expect(t.isDirty(.{ .screen = .{ .x = 0, .y = 0 } }));\n\n    // Assert various properties about our screen to verify\n    // we have all expected cells.\n    {\n        const list_cell = t.screens.active.pages.getCell(.{ .screen = .{ .x = 0, .y = 0 } }).?;\n        const cell = list_cell.cell;\n        try testing.expectEqual(@as(u21, 0x1F468), cell.content.codepoint);\n        try testing.expect(cell.hasGrapheme());\n        try testing.expectEqual(Cell.Wide.wide, cell.wide);\n        const cps = list_cell.node.data.lookupGrapheme(cell).?;\n        try testing.expectEqual(@as(usize, 4), cps.len);\n    }\n    {\n        const list_cell = t.screens.active.pages.getCell(.{ .screen = .{ .x = 1, .y = 0 } }).?;\n        const cell = list_cell.cell;\n        try testing.expectEqual(@as(u21, 0), cell.content.codepoint);\n        try testing.expect(!cell.hasGrapheme());\n        try testing.expectEqual(Cell.Wide.spacer_tail, cell.wide);\n    }\n}"
}
