{
  "suite": "ghostty",
  "file": "Terminal.zig",
  "testName": "Terminal: carriage return origin mode moves to left margin",
  "sourceLine": 6067,
  "zigBody": "test \"Terminal: carriage return origin mode moves to left margin\" {\n    var t = try init(testing.allocator, .{ .cols = 5, .rows = 80 });\n    defer t.deinit(testing.allocator);\n\n    t.modes.set(.origin, true);\n    t.screens.active.cursor.x = 0;\n    t.scrolling_region.left = 2;\n    t.carriageReturn();\n    try testing.expectEqual(@as(usize, 2), t.screens.active.cursor.x);\n}"
}
