{
  "suite": "ghostty",
  "file": "PageList.zig",
  "testName": "PageList highlightSemanticContent output no output returns null",
  "sourceLine": 9421,
  "zigBody": "test \"PageList highlightSemanticContent output no output returns null\" {\n    const testing = std.testing;\n    const alloc = testing.allocator;\n\n    var s = try init(alloc, 10, 20, 0);\n    defer s.deinit();\n    try testing.expect(s.pages.first == s.pages.last);\n    const page = &s.pages.first.?.data;\n\n    // Prompt on row 5 with only prompt and input, no output\n    {\n        const rac = page.getRowAndCell(0, 5);\n        rac.row.semantic_prompt = .prompt;\n\n        // First 3 cols are prompt\n        for (0..3) |x| {\n            const cell = page.getRowAndCell(x, 5).cell;\n            cell.* = .{\n                .content_tag = .codepoint,\n                .content = .{ .codepoint = '$' },\n                .semantic_content = .prompt,\n            };\n        }\n\n        // Rest is input (must explicitly mark all cells to avoid default .output)\n        for (3..10) |x| {\n            const cell = page.getRowAndCell(x, 5).cell;\n            cell.* = .{\n                .content_tag = .codepoint,\n                .content = .{ .codepoint = 'c' },\n                .semantic_content = .input,\n            };\n        }\n    }\n    // Mark rows 6-9 as input to ensure no output between prompts\n    {\n        for (6..10) |y| {\n            for (0..10) |x| {\n                const cell = page.getRowAndCell(x, y).cell;\n                cell.semantic_content = .input;\n            }\n        }\n    }\n    // Prompt on row 10 (no output between prompts)\n    {\n        const rac = page.getRowAndCell(0, 10);\n        rac.row.semantic_prompt = .prompt;\n    }\n\n    // Highlighting output should return null when there's no output\n    const hl = s.highlightSemanticContent(\n        s.pin(.{ .screen = .{ .x = 0, .y = 5 } }).?,\n        .output,\n    );\n    try testing.expect(hl == null);\n}"
}
