{
  "suite": "ghostty",
  "file": "PageList.zig",
  "testName": "PageList clone partial trimmed left reclaims styles",
  "sourceLine": 10042,
  "zigBody": "test \"PageList clone partial trimmed left reclaims styles\" {\n    const testing = std.testing;\n    const alloc = testing.allocator;\n\n    var s = try init(alloc, 80, 20, null);\n    defer s.deinit();\n    try testing.expectEqual(@as(usize, s.rows), s.totalRows());\n    try s.growRows(30);\n\n    // Style the rows we're trimming\n    {\n        try testing.expect(s.pages.first == s.pages.last);\n        const page = &s.pages.first.?.data;\n\n        const style: stylepkg.Style = .{ .flags = .{ .bold = true } };\n        const style_id = try page.styles.add(page.memory, style);\n\n        var it = s.rowIterator(.left_up, .{ .screen = .{} }, .{ .screen = .{ .y = 9 } });\n        while (it.next()) |p| {\n            const rac = p.rowAndCell();\n            rac.row.styled = true;\n            rac.cell.* = .{\n                .content_tag = .codepoint,\n                .content = .{ .codepoint = 'A' },\n                .style_id = style_id,\n            };\n            page.styles.use(page.memory, style_id);\n        }\n\n        // We're over-counted by 1 because `add` implies `use`.\n        page.styles.release(page.memory, style_id);\n\n        // Expect to have one style\n        try testing.expectEqual(1, page.styles.count());\n    }\n\n    var s2 = try s.clone(alloc, .{\n        .top = .{ .screen = .{ .y = 10 } },\n    });\n    defer s2.deinit();\n    try testing.expectEqual(@as(usize, 40), s2.totalRows());\n\n    {\n        try testing.expect(s2.pages.first == s2.pages.last);\n        const page = &s2.pages.first.?.data;\n        try testing.expectEqual(0, page.styles.count());\n    }\n}"
}
